encryptutils/__init__.py
encryptutils-0.1.2b0.dist-info/LICENSE
encryptutils-0.1.2b0.dist-info/METADATA
encryptutils-0.1.2b0.dist-info/WHEEL
encryptutils-0.1.2b0.dist-info/top_level.txt
encryptutils-0.1.2b0.dist-info/RECORD
