Metadata-Version: 2.1
Name: encryptutils
Version: 0.1.2b0
Summary: A small encrypting/decrypting toolkit which includes support for strings and files.
Author-email: AfterNoonPM <h2o.Drop2010+pypi@gmail.com>
License: MIT License        
Project-URL: Homepage, https://github.com/tinkering-townsperson/encryptutils
Project-URL: Bug Tracker, https://github.com/tinkering-townsperson/encryptutils/issues
Classifier: Programming Language :: Python :: 3
Classifier: License :: OSI Approved :: MIT License
Classifier: Operating System :: OS Independent
Requires-Python: >=3.6
License-File: LICENSE
Requires-Dist: cryptography
